ChaProEV/ChaProEV.py
ChaProEV/__init__.py
ChaProEV/charging.py
ChaProEV/consumption.py
ChaProEV/define.py
ChaProEV/make_variants.py
ChaProEV/mobility.py
ChaProEV/py.typed
ChaProEV/run_time.py
ChaProEV/weather.py
ChaProEV/writing.py
ChaProEV-1.0.8.dist-info/LICENCE
ChaProEV-1.0.8.dist-info/METADATA
ChaProEV-1.0.8.dist-info/PKG-INFO-PC-28624
ChaProEV-1.0.8.dist-info/PKG-INFO-PC-28624-2
ChaProEV-1.0.8.dist-info/SOURCES-PC-28624-2.txt
ChaProEV-1.0.8.dist-info/SOURCES-PC-28624.txt
ChaProEV-1.0.8.dist-info/WHEEL
ChaProEV-1.0.8.dist-info/requires-PC-28624-2.txt
ChaProEV-1.0.8.dist-info/requires-PC-28624.txt
ChaProEV-1.0.8.dist-info/top_level.txt
ChaProEV-1.0.8.dist-info/RECORD
